spencer_funcs/__init__.py
spencer_funcs/autodiscovery.py
spencer_funcs/lazy.py
spencer_funcs-0.0.5.dist-info/LICENSE.md
spencer_funcs-0.0.5.dist-info/METADATA
spencer_funcs-0.0.5.dist-info/WHEEL
spencer_funcs-0.0.5.dist-info/top_level.txt
spencer_funcs-0.0.5.dist-info/RECORD
