Metadata-Version: 2.2
Name: spencer_funcs
Version: 0.0.5
Summary: TODO edit me
Home-page: https://github.com/spencer-hanson/spencer-funcs
Author: Spencer Hanson
Classifier: Programming Language :: Python :: 3
License-File: LICENSE.md
Dynamic: author
Dynamic: classifier
Dynamic: description
Dynamic: home-page
Dynamic: summary
